pywe_subscribe_message/__init__.py
pywe_subscribe_message/subscribemsg.py
pywe_subscribe_message-1.0.1.dist-info/METADATA
pywe_subscribe_message-1.0.1.dist-info/WHEEL
pywe_subscribe_message-1.0.1.dist-info/top_level.txt
pywe_subscribe_message-1.0.1.dist-info/RECORD
